example_package_anavarro2/__init__.py
example_package_anavarro2/main.py
example_package_anavarro2-0.0.3.dist-info/METADATA
example_package_anavarro2-0.0.3.dist-info/WHEEL
example_package_anavarro2-0.0.3.dist-info/RECORD
