Metadata-Version: 2.4
Name: example_package_anavarro2
Version: 0.0.3
Summary: Suma de numero
Project-URL: Homepage, https://github.com/pypa/sampleproject
Project-URL: Issues, https://github.com/pypa/sampleproject/issues
Author-email: Alvaro <a.navarrogg@gmail.com>
License: MIT
Classifier: Operating System :: OS Independent
Classifier: Programming Language :: Python :: 3
Requires-Python: >=3.8
